tests/__init__.py
tests/test_box_alteration.py
tests/test_coco_format_manifest.py
tests/test_dataset_downloader.py
tests/test_dataset_manifest.py
tests/test_dataset_registry.py
tests/test_detection_as_classification.py
tests/test_file_reader.py
tests/test_fixtures.py
tests/test_ic_od_as_image_text_dataset.py
tests/test_iris_format_manifest.py
tests/test_manifest_dataset.py
tests/test_utils.py
tests/resources/__init__.py
tests/resources/util.py
tests/test_coco_adaptor/__init__.py
tests/test_coco_adaptor/coco_adaptor_base.py
tests/test_coco_adaptor/test_image_caption_coco_manifest_adaptor.py
tests/test_coco_adaptor/test_image_matting_coco_manifest_adaptor.py
tests/test_coco_adaptor/test_image_regression_coco_manifest_adaptor.py
tests/test_coco_adaptor/test_image_text_matching_coco_manifest_adaptor.py
tests/test_coco_adaptor/test_key_value_pair_coco_manifest_adaptor.py
tests/test_coco_adaptor/test_multiclass_classification_coco_manifest_adaptor.py
tests/test_coco_adaptor/test_multilabel_classification_coco_manifest_adaptor.py
tests/test_coco_adaptor/test_multitask_coco_manifest_adaptor.py
tests/test_coco_adaptor/test_object_detection_coco_manifest_adaptor.py
tests/test_coco_adaptor/test_text_2_image_retrieval_coco_manifest_adaptor.py
tests/test_coco_adaptor/test_visual_object_grounding_coco_manifest_adaptor.py
tests/test_coco_adaptor/test_visual_question_anwsering_coco_manifest_adaptor.py
tests/test_manifest/__init__.py
tests/test_manifest/test_key_value_pair.py
tests/test_manifest/test_pickleable.py
tests/test_manifest/test_visual_object_grounding.py
tests/test_manifest_to_coco/__init__.py
tests/test_manifest_to_coco/test_manifest_to_coco.py
tests/test_merge_manifest/__init__.py
tests/test_merge_manifest/test_manifest_merge.py
tests/test_sample/__init__.py
tests/test_sample/test_sample_manfiest.py
tests/test_spawn/__init__.py
tests/test_spawn/test_spawn.py
tests/test_stand_along_image_dict_generation/__init__.py
vision_datasets-1.0.21.dist-info/licenses/LICENSE
vision_datasets-1.0.21.dist-info/METADATA
vision_datasets-1.0.21.dist-info/WHEEL
vision_datasets-1.0.21.dist-info/entry_points.txt
vision_datasets-1.0.21.dist-info/top_level.txt
vision_datasets-1.0.21.dist-info/RECORD
