Metadata-Version: 2.4
Name: vision_datasets
Version: 1.0.21
Summary: A utility repo for vision dataset access and management.
Home-page: https://github.com/microsoft/vision-datasets
Author: Ping Jin, Shohei Ono
License: MIT
Keywords: vision datasets classification detection
Classifier: Development Status :: 4 - Beta
Classifier: Intended Audience :: Developers
Classifier: License :: OSI Approved :: MIT License
Classifier: Programming Language :: Python :: 3.8
Classifier: Programming Language :: Python :: 3.9
Classifier: Programming Language :: Python :: 3.10
Requires-Python: >=3.8
License-File: LICENSE
Requires-Dist: azure-identity
Requires-Dist: azure-storage-blob
Requires-Dist: numpy>=1.18.3
Requires-Dist: Pillow>=6.2.2
Requires-Dist: requests>=2.23.0
Requires-Dist: tenacity>=6.2.0
Requires-Dist: tqdm
Provides-Extra: torch
Requires-Dist: torch>=1.6.0; extra == "torch"
Provides-Extra: plot
Requires-Dist: matplotlib; extra == "plot"
Dynamic: author
Dynamic: classifier
Dynamic: description
Dynamic: description-content-type
Dynamic: home-page
Dynamic: keywords
Dynamic: license
Dynamic: license-file
Dynamic: provides-extra
Dynamic: requires-dist
Dynamic: requires-python
Dynamic: summary
